[
  {
    "id": "51-1",
    "title": "Drug-Induced AIN",
    "brick_id": "51",
    "brick_title": "Acute Interstitial Nephritis",
    "week": 3,
    "type": "disease",
    "buzzwords": [
      "rising creatinine",
      "new drug",
      "fever/rash/eos",
      "7-10 day lag",
      "WBC casts",
      "drug as hapten",
      "NSAIDs/PPIs/penicillins",
      "stop the drug"
    ]
  },
  {
    "id": "51-2",
    "title": "Infection-Induced AIN",
    "brick_id": "51",
    "brick_title": "Acute Interstitial Nephritis",
    "week": 3,
    "type": "disease",
    "buzzwords": [
      "AKI",
      "no drug trigger",
      "sterile pyuria",
      "WBC casts",
      "no allergic triad",
      "nonallergic infiltrate",
      "bacterial pyelo",
      "steroids unhelpful"
    ]
  },
  {
    "id": "51-3",
    "title": "Autoimmune AIN",
    "brick_id": "51",
    "brick_title": "Acute Interstitial Nephritis",
    "week": 3,
    "type": "disease",
    "buzzwords": [
      "intrarenal AKI",
      "sterile pyuria",
      "no recent drug",
      "noncaseating granulomas",
      "sicca symptoms",
      "malar rash",
      "sarcoid/Sjogren/SLE",
      "treat underlying"
    ]
  }
]
