[
  {
    "id": "bloodlymph-35-1",
    "title": "Yersinia pestis",
    "course": "bloodlymph",
    "brick_id": "35",
    "brick_title": "Y. pestis, F. tularemia, and B. henselae",
    "type": "disease",
    "buzzwords": [
      "zoonotic infection",
      "flea bite",
      "rodent reservoir",
      "endemic western US",
      "facultative intracellular",
      { "img": "data/bloodlymph/images/35/bloodlymph-35-1-stain.webp" },
      { "img": "data/bloodlymph/images/35/bloodlymph-35-1-bubo.webp" },
      "the plague"
    ]
  },
  {
    "id": "bloodlymph-35-2",
    "title": "Francisella tularensis",
    "course": "bloodlymph",
    "brick_id": "35",
    "brick_title": "Y. pestis, F. tularemia, and B. henselae",
    "type": "disease",
    "buzzwords": [
      "zoonotic infection",
      "tiny infectious dose",
      "rabbit contact",
      "tick or deerfly bite",
      { "img": "data/bloodlymph/images/35/bloodlymph-35-2-map.webp" },
      { "img": "data/bloodlymph/images/35/bloodlymph-35-2-ulcer.webp" },
      "cysteine charcoal agar",
      "rabbit fever"
    ]
  },
  {
    "id": "bloodlymph-35-3",
    "title": "Bartonella henselae",
    "course": "bloodlymph",
    "brick_id": "35",
    "brick_title": "Y. pestis, F. tularemia, and B. henselae",
    "type": "disease",
    "buzzwords": [
      "zoonotic infection",
      "cat scratch or bite",
      "regional lymphadenopathy",
      { "img": "data/bloodlymph/images/35/bloodlymph-35-3-papule.webp" },
      "necrotizing granulomas",
      "bacillary angiomatosis if immunocompromised",
      { "img": "data/bloodlymph/images/35/bloodlymph-35-3-ba.webp" },
      "cat scratch disease"
    ]
  }
]
